iot_db/__init__.py
iot_db/models/__init__.py
iot_db/models/alert.py
iot_db/models/base.py
iot_db/models/electricity.py
iot_db/models/heat.py
iot_db/models/py.typed
iot_db/models/raw.py
iot_db/models/temperature.py
iot_db/models/water.py
iot_db/models/dimensions/__init__.py
iot_db/models/dimensions/channel_function.py
iot_db/models/dimensions/data_source.py
iot_db/models/dimensions/date.py
iot_db/models/dimensions/device.py
iot_db/models/dimensions/time.py
iot_db/models/facts/__init__.py
iot_db/models/facts/measurement.py
iot_db/models/facts/state.py
iot_db/models/facts/usage.py
iot_db/scripts/__init__.py
iot_db/scripts/populate_dim_date.py
iot_db/scripts/populate_dim_time.py
iot_db/scripts/seed_dimension_data.py
ngits_iot_db-0.4.2.dist-info/licenses/LICENSE
ngits_iot_db-0.4.2.dist-info/METADATA
ngits_iot_db-0.4.2.dist-info/WHEEL
ngits_iot_db-0.4.2.dist-info/top_level.txt
ngits_iot_db-0.4.2.dist-info/RECORD
